{
    "type":  "FeatureCollection",
    "name":  "uav_position",
    "crs":  {
                "type":  "name",
                "properties":  {
                                   "name":  "urn:ogc:def:crs:OGC:1.3:CRS84"
                               }
            },
    "features":  [
                     {
                         "type":  "Feature",
                         "geometry":  {
                                          "coordinates":  [
                                                              116.1755,
                                                              39.1635,
                                                              125.0
                                                          ],
                                          "type":  "Point"
                                      },
                         "properties":  {
                                            "id":  "uav_current_mock",
                                            "name":  "Current UAV mock position",
                                            "task_id":  "task_001",
                                            "source":  "demo_current_uav",
                                            "altitude_m":  125.0,
                                            "capture_time_s":  74
                                        }
                     }
                 ]
}